Py_Thanglish.py
Py_Thanglish-0.0.4.dist-info/LICENCE.txt
Py_Thanglish-0.0.4.dist-info/METADATA
Py_Thanglish-0.0.4.dist-info/WHEEL
Py_Thanglish-0.0.4.dist-info/top_level.txt
Py_Thanglish-0.0.4.dist-info/RECORD
