Metadata-Version: 2.1
Name: Py-Thanglish
Version: 0.0.4
Summary: Tamil to Thanglish converter in python
Home-page: UNKNOWN
Author: Dayanidi Vadivel
Author-email: dayanidivadivel@gmail.com
License: MIT
Keywords: Thanglish,Tamil to Thanglish in python,Thanglish pip,Py_Thanglish,Py-Thanglish,Py_Thanglish pip,Py-Thanglish pip,pip Py_Thanglish,pip Py-Thanglish,py_thanglish,py-thanglish,pythanglish,pythanglish
Platform: UNKNOWN
Classifier: Programming Language :: Python :: 3
Classifier: License :: OSI Approved :: MIT License
Classifier: Operating System :: OS Independent
Requires: pandas
